<PAMDataset>
  <PAMRasterBand band="1">
    <Description>Layer_1</Description>
    <Metadata>
      <MDI key="LAYER_TYPE">athematic</MDI>
      <MDI key="STATISTICS_MAXIMUM">960</MDI>
      <MDI key="STATISTICS_MEAN">386.2396459878</MDI>
      <MDI key="STATISTICS_MINIMUM">15</MDI>
      <MDI key="STATISTICS_STDDEV">368.65632015277</MDI>
    </Metadata>
  </PAMRasterBand>
  <PAMRasterBand band="2">
    <Description>Layer_2</Description>
    <Metadata>
      <MDI key="LAYER_TYPE">athematic</MDI>
      <MDI key="STATISTICS_MAXIMUM">998</MDI>
      <MDI key="STATISTICS_MEAN">363.85881139258</MDI>
      <MDI key="STATISTICS_MINIMUM">0</MDI>
      <MDI key="STATISTICS_STDDEV">406.80813750845</MDI>
    </Metadata>
  </PAMRasterBand>
</PAMDataset>
